{
  "main": {
    "id": "b28d393bc3829e9e",
    "type": "split",
    "children": [
      {
        "id": "de3e2949e5858d8b",
        "type": "tabs",
        "children": [
          {
            "id": "ca7293113f959fd7",
            "type": "leaf",
            "state": {
              "type": "markdown",
              "state": {
                "file": "电路/数字电路/信息表示.md",
                "mode": "source",
                "source": false
              },
              "icon": "lucide-file",
              "title": "信息表示"
            }
          }
        ]
      }
    ],
    "direction": "vertical"
  },
  "left": {
    "id": "0d1c499758cedec5",
    "type": "split",
    "children": [
      {
        "id": "c396d14e0e7df5bf",
        "type": "tabs",
        "children": [
          {
            "id": "be2776a3da41cfbd",
            "type": "leaf",
            "state": {
              "type": "file-explorer",
              "state": {
                "sortOrder": "alphabetical",
                "autoReveal": false
              },
              "icon": "lucide-folder-closed",
              "title": "文件列表"
            }
          },
          {
            "id": "a735507991bd5b6a",
            "type": "leaf",
            "state": {
              "type": "search",
              "state": {
                "query": "定比",
                "matchingCase": false,
                "explainSearch": false,
                "collapseAll": false,
                "extraContext": false,
                "sortOrder": "alphabetical"
              },
              "icon": "lucide-search",
              "title": "搜索"
            }
          },
          {
            "id": "b04faceddc4382b7",
            "type": "leaf",
            "state": {
              "type": "bookmarks",
              "state": {},
              "icon": "lucide-bookmark",
              "title": "书签"
            }
          }
        ]
      }
    ],
    "direction": "horizontal",
    "width": 255.5
  },
  "right": {
    "id": "0344e99f2048f017",
    "type": "split",
    "children": [
      {
        "id": "1d46ced9feed9b0f",
        "type": "tabs",
        "children": [
          {
            "id": "d5379f097bc81ba0",
            "type": "leaf",
            "state": {
              "type": "backlink",
              "state": {
                "file": "电路/数字电路/信息表示.md",
                "collapseAll": false,
                "extraContext": false,
                "sortOrder": "alphabetical",
                "showSearch": false,
                "searchQuery": "",
                "backlinkCollapsed": false,
                "unlinkedCollapsed": true
              },
              "icon": "links-coming-in",
              "title": "信息表示 的反向链接列表"
            }
          },
          {
            "id": "42986b894c2bbf85",
            "type": "leaf",
            "state": {
              "type": "outgoing-link",
              "state": {
                "file": "电路/数字电路/信息表示.md",
                "linksCollapsed": false,
                "unlinkedCollapsed": true
              },
              "icon": "links-going-out",
              "title": "信息表示 的出链列表"
            }
          },
          {
            "id": "dda4175c462f9f23",
            "type": "leaf",
            "state": {
              "type": "tag",
              "state": {
                "sortOrder": "frequency",
                "useHierarchy": true,
                "showSearch": false,
                "searchQuery": ""
              },
              "icon": "lucide-tags",
              "title": "标签"
            }
          },
          {
            "id": "b0d0bcdce11bb7b9",
            "type": "leaf",
            "state": {
              "type": "outline",
              "state": {
                "file": "电路/数字电路/信息表示.md",
                "followCursor": false,
                "showSearch": false,
                "searchQuery": ""
              },
              "icon": "lucide-list",
              "title": "信息表示 的大纲"
            }
          },
          {
            "id": "6ce1b8f2b05dbbb8",
            "type": "leaf",
            "state": {
              "type": "graph",
              "state": {},
              "icon": "lucide-git-fork",
              "title": "关系图谱"
            }
          }
        ],
        "currentTab": 4
      }
    ],
    "direction": "horizontal",
    "width": 433.5
  },
  "left-ribbon": {
    "hiddenItems": {
      "obsidian-excalidraw-plugin:新建绘图文件": false,
      "switcher:打开快速切换": false,
      "graph:查看关系图谱": false,
      "canvas:新建白板": false,
      "daily-notes:打开/创建今天的日记": false,
      "templates:插入模板": false,
      "command-palette:打开命令面板": false,
      "bases:创建新数据库": false,
      "workspaces:管理工作区布局": false,
      "random-note:开始漫游笔记": false
    }
  },
  "active": "ca7293113f959fd7",
  "lastOpenFiles": [
    "电路/数字电路/模型机.md",
    "电路/数字电路/逻辑运算.md",
    "电路/模拟电路/运放电路/运算放大器.md",
    "电路/模拟电路/运放电路/运算电路.md",
    "电路/模拟电路/运放电路/放大电路.md",
    "attachment/Pasted image 20251025203008.png",
    "attachment/Pasted image 20251025202955.png",
    "attachment/Pasted image 20251025202014.png",
    "attachment/Pasted image 20251025201958.png",
    "电路/电路基本定理/戴维南定理.md",
    "电路/电路基本定理/诺顿定理.md",
    "电路/电路基本定理/线性电路.md",
    "attachment/Pasted image 20251025195036.png",
    "电路/模拟电路/电路分析/频率响应.md",
    "电路/模拟电路/电路分析/阻抗.md",
    "attachment/Pasted image 20251025192331.png",
    "attachment/Pasted image 20251025192318.png",
    "attachment/Pasted image 20251025192304.png",
    "电路/模拟电路/电路分析/复指数分析法.md",
    "电路/模拟电路/CMOS/CMOS.md",
    "电路/数字电路/数字抽象/加法器.md",
    "电路/数字电路/数字抽象/逻辑运算律.md",
    "电路/数字电路/信息表示.md",
    "电路/模拟电路/CMOS/MOSFET放大器.md",
    "电路/模拟电路/CMOS/MOSFET工作原理.md",
    "电路/模拟电路/CMOS/PN结的偏置.md",
    "电路/模拟电路/CMOS/MOSFET开关.md",
    "电路/电路基本定理/叠加定理.md",
    "电路/模拟电路/电路分析/滤波器.md",
    "电路/模拟电路/运放电路/反馈.md",
    "数学/基础课程/解析几何/几何空间的度量/定比分点.md",
    "数学/数学竞赛/无穷级数/傅里叶级数/基础/正交性.md",
    "数学/数学竞赛/无穷级数/傅里叶级数/基础/傅里叶级数.md",
    "物理/电磁学/电流场/电流动力学方程.md",
    "attachment/Pasted image 20251025140506.png",
    "attachment/Pasted image 20251025135100.png",
    "Excalidraw/NotoSansSC-Regular.ttf",
    "Excalidraw/梦源宋体-W5.ttc",
    "Excalidraw/寒蝉正楷体.ttf",
    "Excalidraw/LINESeedSans_Rg.ttf",
    "Excalidraw/CJK Fonts",
    "Excalidraw/新建文件夹",
    "数学/数学竞赛/一元积分/基本方法/一元积分基本方法.canvas",
    "数学/数学竞赛/一元积分/基本方法/未命名.base",
    "数学/基础课程/概率论/多维随机变量/多维随机变量分布/多元正态分布",
    "数学/基础课程/概率论/多维随机变量/多维随机变量分布",
    "数学/基础课程/概率论/多维随机变量",
    "Excalidraw/未命名.canvas",
    "未命名.canvas"
  ]
}